{
  "weekId": "2026-W25",
  "startDate": "2026-06-15",
  "endDate": "2026-06-21",
  "summary": "La settimana dal 15 al 21 giugno 2026 è stata dominata dall'accordo nucleare tra Stati Uniti e Iran, firmato il 18 giugno a Versailles dopo un memorandum di 14 punti siglato il 17 giugno. Il presidente Trump ha però minacciato di riprendere i bombardamenti se l'intesa non lo soddisfa. Già il 21 giugno i negoziati sono ripresi in Svizzera, con tensioni sullo Stretto di Hormuz. Parallelamente, al G7 di Evian (16-17 giugno) Trump ha esortato la Russia a fare un accordo con l'Ucraina, mentre l'Eurocamera ha approvato l'intesa sui dazi UE-USA. Il conflitto russo-ucraino ha visto massicci attacchi notturni il 18 giugno, con la raffineria di Mosca in fiamme. In Medio Oriente, i raid israeliani in Libano si sono intensificati: il 19 giugno 18 morti, il 20 giugno 47 vittime e villaggi rasi al suolo, facendo fuggire la popolazione. Sul fronte interno italiano, l'inchiesta urbanistica di Milano si è conclusa il 17 giugno con l'assoluzione di tutti gli imputati, ma 5.000 famiglie restano in una situazione di incertezza. Sull'immigrazione, il 20 giugno l'Italia ha proposto hub europei in Paesi terzi, provocando uno scontro con il premier spagnolo Sánchez. Nel Regno Unito, le elezioni suppletive del 18 giugno sono state decisive per la leadership laburista e il futuro primo ministro. In Bolivia, lo stato d'emergenza è stato dichiarato il 21 giugno dopo 51 giorni di blocchi stradali che paralizzano il Paese. Tra le storie che sono rapidamente svanite: l'annuncio iniziale di un accordo di pace USA-Iran con riapertura di Hormuz (15 giugno), l'incontro Meloni-Takaichi a Roma (15 giugno), le offerte di acquisizione di American Express per TheFork e Fox per Roku, e l'appello di Trump al G7 per un accordo Russia-Ucraina. Le storie più persistenti sono state il dossier nucleare iraniano, l'escalation Israele-Libano e il conflitto Russia-Ucraina.",
  "persistentStories": [],
  "fadedStories": [
    "Stati Uniti e Iran firmano venerdì l'accordo di pace con riapertura di Hormuz",
    "Meloni accoglie Takaichi a Roma, al centro riapertura di Hormuz e G7",
    "American Express acquisisce TheFork da TripAdvisor per 700 milioni di dollari",
    "Fox lancia offerta da 19,1 miliardi di euro per Roku in contanti e azioni",
    "Trump al G7 di Evian: la Russia deve fare un accordo con l'Ucraina",
    "Eurocamera approva l'accordo sui dazi tra Unione Europea e Stati Uniti",
    "Istat conferma inflazione a +0,4% a maggio e +3,2% su base annua",
    "UniCredit, martedì scade l'offerta ostile per l'acquisto di Commerzbank",
    "Nvidia raccoglie 21,5 miliardi di euro con un bond per investimenti nell'AI",
    "Iran e Stati Uniti firmano un memorandum in 14 punti per l'accordo nucleare"
  ],
  "topHeadlines": [
    {
      "date": "2026-06-15",
      "title": "Stati Uniti e Iran firmano venerdì l'accordo di pace con riapertura di Hormuz",
      "category": "politics",
      "region": "middle-east"
    },
    {
      "date": "2026-06-15",
      "title": "Meloni accoglie Takaichi a Roma, al centro riapertura di Hormuz e G7",
      "category": "politics",
      "region": "europe"
    },
    {
      "date": "2026-06-16",
      "title": "Trump al G7 di Evian: la Russia deve fare un accordo con l'Ucraina",
      "category": "politics",
      "region": "europe"
    },
    {
      "date": "2026-06-16",
      "title": "Eurocamera approva l'accordo sui dazi tra Unione Europea e Stati Uniti",
      "category": "economy",
      "region": "europe"
    },
    {
      "date": "2026-06-17",
      "title": "Iran e Stati Uniti firmano un memorandum in 14 punti per l'accordo nucleare",
      "category": "politics",
      "region": "middle-east"
    },
    {
      "date": "2026-06-17",
      "title": "Trump al G7 minaccia l'Iran: se l'accordo non mi piace torneremo a bombardare",
      "category": "politics",
      "region": "middle-east"
    },
    {
      "date": "2026-06-17",
      "title": "Inchiesta urbanistica a Milano: assolti tutti, ma 5.000 famiglie ancora nel limbo",
      "category": "society",
      "region": "europe"
    },
    {
      "date": "2026-06-18",
      "title": "Russia e Ucraina si colpiscono con massicci attacchi notturni, raffineria di Mosca in fiamme",
      "category": "conflict",
      "region": "europe"
    },
    {
      "date": "2026-06-18",
      "title": "Usa e Iran firmano l'accordo nucleare, Trump sigla il protocollo a Versailles",
      "category": "politics",
      "region": "middle-east"
    },
    {
      "date": "2026-06-18",
      "title": "Regno Unito, elezioni suppletive decisive per la leadership laburista e il futuro premier",
      "category": "politics",
      "region": "europe"
    },
    {
      "date": "2026-06-19",
      "title": "Raid israeliani in Libano uccidono 18 persone, residenti fuggono dai villaggi",
      "category": "conflict",
      "region": "middle-east"
    },
    {
      "date": "2026-06-20",
      "title": "Raid israeliani in Libano: 47 morti in un giorno, villaggi rasi al suolo",
      "category": "conflict",
      "region": "middle-east"
    },
    {
      "date": "2026-06-20",
      "title": "Migranti, Italia propone hub europei nei Paesi terzi: scontro Meloni-Sánchez",
      "category": "society",
      "region": "europe"
    },
    {
      "date": "2026-06-21",
      "title": "USA e Iran riprendono i negoziati in Svizzera, tensione sullo Stretto di Hormuz",
      "category": "politics",
      "region": "middle-east"
    },
    {
      "date": "2026-06-21",
      "title": "Bolivia in stato d'emergenza, blocchi stradali paralizzano il Paese da 51 giorni",
      "category": "politics",
      "region": "americas"
    }
  ],
  "metadata": {
    "totalArticlesProcessed": 1315,
    "totalSourcesUsed": 7,
    "daysWithData": 7,
    "categoryCounts": {
      "politics": 14,
      "economy": 7,
      "science": 6,
      "society": 2,
      "conflict": 6
    },
    "regionCounts": {
      "middle-east": 8,
      "europe": 19,
      "americas": 4,
      "global": 3,
      "asia-pacific": 1
    }
  }
}